utilitools/__init__.py
utilitools/tests/__init__.py
utilitools/tests/test_flatten.py
utilitools/tests/test_islice.py
utilitools/tests/test_partial.py
utilitools/tests/test_singleton.py
utilitools/tests/test_subscription.py
utilitools/utilities/__init__.py
utilitools/utilities/flatten.py
utilitools/utilities/islice.py
utilitools/utilities/partial.py
utilitools/utilities/singleton.py
utilitools/utilities/subscription.py
utilitools-0.0.14.dist-info/LICENSE
utilitools-0.0.14.dist-info/METADATA
utilitools-0.0.14.dist-info/WHEEL
utilitools-0.0.14.dist-info/top_level.txt
utilitools-0.0.14.dist-info/RECORD
