Metadata-Version: 2.1
Name: utilitools
Version: 0.0.14
Summary: A collection of utilities.
Author: Idan Hazan
License: MIT
Project-URL: homepage, https://github.com/idanhazan/utilitools
Project-URL: repository, https://github.com/idanhazan/utilitools
Project-URL: documentation, https://utilitools.readthedocs.io
Keywords: utilities
Classifier: Programming Language :: Python :: 3
Classifier: Topic :: Utilities
Classifier: License :: OSI Approved :: MIT License
Requires-Python: >=3.8
License-File: LICENSE
